icepy4d/__init__.py
icepy4d/__main__.py
icepy4d/classes/__init__.py
icepy4d/classes/calibration.py
icepy4d/classes/camera.py
icepy4d/classes/dsm.py
icepy4d/classes/epoch.py
icepy4d/classes/features.py
icepy4d/classes/images.py
icepy4d/classes/ortophoto.py
icepy4d/classes/point_cloud.py
icepy4d/classes/points.py
icepy4d/classes/sensor_width_database.py
icepy4d/classes/targets.py
icepy4d/classes/typed_dict_classes_old.py
icepy4d/io/__init__.py
icepy4d/io/export2bundler.py
icepy4d/io/export2calge.py
icepy4d/io/export2colmap.py
icepy4d/io/export2textfile.py
icepy4d/io/colmap_utils/__init__.py
icepy4d/io/colmap_utils/build.py
icepy4d/io/colmap_utils/build_windows_app.py
icepy4d/io/colmap_utils/bundler_to_ply.py
icepy4d/io/colmap_utils/clang_format_code.py
icepy4d/io/colmap_utils/crawl_camera_specs.py
icepy4d/io/colmap_utils/database.py
icepy4d/io/colmap_utils/export_inlier_matches.py
icepy4d/io/colmap_utils/export_inlier_pairs.py
icepy4d/io/colmap_utils/export_to_bundler.py
icepy4d/io/colmap_utils/export_to_visualsfm.py
icepy4d/io/colmap_utils/flickr_downloader.py
icepy4d/io/colmap_utils/h5_to_db.py
icepy4d/io/colmap_utils/merge_ply_files.py
icepy4d/io/colmap_utils/nvm_to_ply.py
icepy4d/io/colmap_utils/plyfile.py
icepy4d/io/colmap_utils/read_write_dense.py
icepy4d/io/colmap_utils/read_write_fused_vis.py
icepy4d/io/colmap_utils/read_write_model.py
icepy4d/io/colmap_utils/visualize_model.py
icepy4d/least_squares/__init__.py
icepy4d/least_squares/absolute_orientation.py
icepy4d/least_squares/rototra3d.py
icepy4d/least_squares/utils.py
icepy4d/matching/__init__.py
icepy4d/matching/match_by_preselection.py
icepy4d/matching/match_pairs.py
icepy4d/matching/matching_base.py
icepy4d/matching/retrieve_matches_from_npz.py
icepy4d/matching/superglue_match_simple_old.py
icepy4d/matching/superglue_matcher.py
icepy4d/matching/superglue_tracker.py
icepy4d/matching/templatematch.py
icepy4d/matching/track_matches.py
icepy4d/matching/track_matches_bk.py
icepy4d/matching/tracking_base.py
icepy4d-1.7.0.dist-info/LICENSE.txt
icepy4d-1.7.0.dist-info/METADATA
icepy4d-1.7.0.dist-info/WHEEL
icepy4d-1.7.0.dist-info/top_level.txt
icepy4d-1.7.0.dist-info/RECORD
