Metadata-Version: 2.1
Name: icepy4d
Version: 1.7.0
Summary: 4D Image-based Continuos monitoring of glaciers Evolution with low-cost stereo-cameras and Deep Learning photogrammetry.
Author-email: Francesco Ioli <francesco.ioli@polimi.it>
License: BSD 3-Clause License
Project-URL: Homepage, https://github.com/franioli/icepy4d
Keywords: sfm,4d-reconstruction,glaciers,deep-learning
Classifier: License :: OSI Approved :: MIT License
Classifier: Programming Language :: Python
Classifier: Programming Language :: Python :: 3
Requires-Python: >=3.8
License-File: LICENSE.txt
Requires-Dist: numpy
Requires-Dist: pandas
Requires-Dist: matplotlib
Requires-Dist: opencv-python
Requires-Dist: torch
Requires-Dist: open3d
Requires-Dist: pydegensac
Requires-Dist: scipy
Requires-Dist: exifread
Requires-Dist: tqdm
Requires-Dist: laspy
Requires-Dist: pyyaml
Requires-Dist: easydict
Requires-Dist: kornia
Requires-Dist: lmfit
Requires-Dist: h5py
Provides-Extra: dev
Requires-Dist: flake8 ; extra == 'dev'
Requires-Dist: black ; extra == 'dev'
Requires-Dist: bumpver ; extra == 'dev'
Requires-Dist: isort ; extra == 'dev'
Requires-Dist: pip-tools ; extra == 'dev'
Requires-Dist: pytest ; extra == 'dev'
Requires-Dist: mkdocs ; extra == 'dev'
Requires-Dist: mkdocs-material ; extra == 'dev'
Requires-Dist: mkdocstrings[python] ; extra == 'dev'
Requires-Dist: pre-commit ; extra == 'dev'
Requires-Dist: nbstripout ; extra == 'dev'
Requires-Dist: build ; extra == 'dev'
Requires-Dist: twine ; extra == 'dev'
